{"cameraMode":{"drawMode":0,"name":"Shaded","section":"Shading Mode"},"sceneLighting":true,"audioPlay":false,"sceneViewState":{"m_AlwaysRefresh":false,"showFog":true,"showSkybox":true,"showFlares":true,"showImageEffects":true,"showParticleSystems":true,"showVisualEffectGraphs":true,"m_FxEnabled":true},"in2DMode":false,"pivot":{"x":4.0,"y":0.0,"z":6.0},"rotation":{"x":0.35476189851760867,"y":0.34486785531044009,"z":-0.14275845885276795,"w":0.8572342991828919},"size":1.9986658096313477,"orthographic":false}